benchmarks/__init__.py
benchmarks/benchmark_sbd_tools.py
benchmarks/bigtext_speed_benchmark.py
benchmarks/english_golden_rules.py
benchmarks/genia_benchmark.py
pysbd/__init__.py
pysbd/abbreviation_replacer.py
pysbd/about.py
pysbd/between_punctuation.py
pysbd/cleaner.py
pysbd/exclamation_words.py
pysbd/languages.py
pysbd/lists_item_replacer.py
pysbd/processor.py
pysbd/punctuation_replacer.py
pysbd/segmenter.py
pysbd/utils.py
pysbd/clean/__init__.py
pysbd/clean/rules.py
pysbd/lang/__init__.py
pysbd/lang/amharic.py
pysbd/lang/arabic.py
pysbd/lang/armenian.py
pysbd/lang/bulgarian.py
pysbd/lang/burmese.py
pysbd/lang/chinese.py
pysbd/lang/danish.py
pysbd/lang/deutsch.py
pysbd/lang/dutch.py
pysbd/lang/english.py
pysbd/lang/french.py
pysbd/lang/greek.py
pysbd/lang/hindi.py
pysbd/lang/italian.py
pysbd/lang/japanese.py
pysbd/lang/kazakh.py
pysbd/lang/marathi.py
pysbd/lang/persian.py
pysbd/lang/polish.py
pysbd/lang/russian.py
pysbd/lang/slovak.py
pysbd/lang/spanish.py
pysbd/lang/urdu.py
pysbd/lang/common/__init__.py
pysbd/lang/common/common.py
pysbd/lang/common/standard.py
pysbd_yurts-0.3.4.dist-info/LICENSE
pysbd_yurts-0.3.4.dist-info/METADATA
pysbd_yurts-0.3.4.dist-info/WHEEL
pysbd_yurts-0.3.4.dist-info/entry_points.txt
pysbd_yurts-0.3.4.dist-info/top_level.txt
pysbd_yurts-0.3.4.dist-info/RECORD
