Metadata-Version: 2.1
Name: pysbd-yurts
Version: 0.3.4
Summary: pysbd (Python Sentence Boundary Disambiguation) is a rule-based sentence boundary detection that works out-of-the-box across many languages.
Home-page: http://nipunsadvilkar.github.io/
Author: Nipun Sadvilkar
Author-email: nipunsadvilkar@gmail.com
License: MIT
Keywords: natural-language-processing nlp
Classifier: Intended Audience :: Developers
Classifier: Intended Audience :: Science/Research
Classifier: Topic :: Scientific/Engineering
Classifier: Topic :: Scientific/Engineering :: Artificial Intelligence
Classifier: Topic :: Scientific/Engineering :: Information Analysis
Classifier: Topic :: Text Processing
Classifier: Topic :: Text Processing :: Linguistic
Classifier: Topic :: Software Development
Classifier: Topic :: Software Development :: Libraries
Classifier: Programming Language :: Python :: 3
Classifier: Programming Language :: Python :: 3.5
Classifier: Programming Language :: Python :: 3.6
Classifier: Programming Language :: Python :: 3.7
Classifier: Programming Language :: Python :: 3.8
Classifier: License :: OSI Approved :: MIT License
Requires-Python: >=3
License-File: LICENSE
